life_model/__init__.py
life_model/__main__.py
life_model/__meta__.py
life_model/base_classes.py
life_model/lifeevents.py
life_model/limits.py
life_model/model.py
life_model/registry.py
life_model/account/__init__.py
life_model/account/bank.py
life_model/account/brokerage.py
life_model/account/hsa.py
life_model/account/job401k.py
life_model/account/pension.py
life_model/account/roth_IRA.py
life_model/account/traditional_IRA.py
life_model/charity/__init__.py
life_model/charity/daf.py
life_model/charity/donation.py
life_model/config/__init__.py
life_model/config/base_config.py
life_model/config/config_manager.py
life_model/config/financial_config.py
life_model/config/models.py
life_model/config/scenarios.py
life_model/debt/__init__.py
life_model/debt/car_loan.py
life_model/debt/credit_card.py
life_model/debt/student_loan.py
life_model/dependents/__init__.py
life_model/dependents/child.py
life_model/dependents/plan529.py
life_model/housing/__init__.py
life_model/housing/apartment.py
life_model/housing/home.py
life_model/insurance/__init__.py
life_model/insurance/annuity.py
life_model/insurance/general_insurance.py
life_model/insurance/life_insurance.py
life_model/insurance/social_security.py
life_model/services/__init__.py
life_model/services/payment_service.py
life_model/services/tax_calculation_service.py
life_model/tax/__init__.py
life_model/tax/federal.py
life_model/tax/fica.py
life_model/tax/state.py
life_model/tax/tax.py
life_model-0.2.0.dist-info/licenses/LICENSE
life_model-0.2.0.dist-info/METADATA
life_model-0.2.0.dist-info/WHEEL
life_model-0.2.0.dist-info/top_level.txt
life_model-0.2.0.dist-info/RECORD
